TestProgramURFU/__init__.py
TestProgramURFU/common_functions.py
TestProgramURFU/db_functions.py
TestProgramURFU-0.1.dist-info/METADATA
TestProgramURFU-0.1.dist-info/WHEEL
TestProgramURFU-0.1.dist-info/top_level.txt
TestProgramURFU-0.1.dist-info/RECORD
