Metadata-Version: 2.1
Name: TestProgramURFU
Version: 0.1
Summary: The Best ever seen
Author: Nikolai
Author-email: ch_k@mail.com
License: UNKNOWN
Platform: UNKNOWN
